al360_trustworthyai/__init__.py
al360_trustworthyai/__version__.py
al360_trustworthyai/_data_validations.py
al360_trustworthyai/_interfaces.py
al360_trustworthyai/exceptions.py
al360_trustworthyai/feature_metadata.py
al360_trustworthyai/serialization_utilities.py
al360_trustworthyai/utils.py
al360_trustworthyai/_config/__init__.py
al360_trustworthyai/_config/base_config.py
al360_trustworthyai/_internal/__init__.py
al360_trustworthyai/_internal/_forecasting_wrappers.py
al360_trustworthyai/_internal/_served_model_wrapper.py
al360_trustworthyai/_internal/constants.py
al360_trustworthyai/_tools/__init__.py
al360_trustworthyai/_tools/causal/__init__.py
al360_trustworthyai/_tools/causal/causal_config.py
al360_trustworthyai/_tools/causal/causal_constants.py
al360_trustworthyai/_tools/causal/causal_result.py
al360_trustworthyai/_tools/causal/dashboard_schemas/__init__.py
al360_trustworthyai/_tools/causal/dashboard_schemas/schema_0.1.0.json
al360_trustworthyai/_tools/counterfactual/__init__.py
al360_trustworthyai/_tools/counterfactual/dashboard_schemas/__init__.py
al360_trustworthyai/_tools/counterfactual/dashboard_schemas/counterfactual_examples_output_v1.0.json
al360_trustworthyai/_tools/counterfactual/dashboard_schemas/counterfactual_examples_output_v2.0.json
al360_trustworthyai/_tools/error_analysis/__init__.py
al360_trustworthyai/_tools/error_analysis/dashboard_schemas/__init__.py
al360_trustworthyai/_tools/error_analysis/dashboard_schemas/error_analysis_output_v0.0.json
al360_trustworthyai/_tools/shared/__init__.py
al360_trustworthyai/_tools/shared/attribute_serialization.py
al360_trustworthyai/_tools/shared/base_result.py
al360_trustworthyai/_tools/shared/state_directory_management.py
al360_trustworthyai/_tools/shared/versions.py
al360_trustworthyai/al360_tai_insights/__init__.py
al360_trustworthyai/al360_tai_insights/al360_tai_base_insights.py
al360_trustworthyai/al360_tai_insights/al360_tai_insights.py
al360_trustworthyai/databalanceanalysis/__init__.py
al360_trustworthyai-0.0.2.dist-info/LICENSE
al360_trustworthyai-0.0.2.dist-info/METADATA
al360_trustworthyai-0.0.2.dist-info/WHEEL
al360_trustworthyai-0.0.2.dist-info/top_level.txt
al360_trustworthyai-0.0.2.dist-info/RECORD
